{
    "profile" : [
        {
        "email": "moghadasishakila239@gmail.com" ,
        "password": "1378"
        }
    ],
    "products": [
        {
            "author": "Chinua Achebe",
            "country": "Nigeria",
            "imageLink": "https://images-na.ssl-images-amazon.com/images/I/81vlAVbRl3L.jpg",
            "language": "English",
            "link": "https://en.wikipedia.org/wiki/Things_Fall_Apart\n",
            "pages": 209,
            "title": "Things Fall Apart",
            "year": 1958
          },
          {
            "author": "Hans Christian Andersen",
            "country": "Denmark",
            "imageLink": "https://www.booksbeyond.co.id/image/cache/products/531/9781405315531-2042x2560.jpg.webp",
            "language": "Danish",
            "link": "https://en.wikipedia.org/wiki/Fairy_Tales_Told_for_Children._First_Collection.\n",
            "pages": 784,
            "title": "Fairy tales",
            "year": 1836
          },
          {
            "author": "Dante Alighieri",
            "country": "Italy",
            "imageLink": "https://m.media-amazon.com/images/M/MV5BYWFkMGIxYWQtOTExNS00NjNjLTkzOGEtYzQzMDkzODllY2Q5XkEyXkFqcGdeQXVyNjI2NTcyNzU@._V1_.jpg",
            "language": "Italian",
            "link": "https://en.wikipedia.org/wiki/Divine_Comedy\n",
            "pages": 928,
            "title": "The Divine Comedy",
            "year": 1315
          },
          {
            "author": "Unknown",
            "country": "Sumer and Akkadian Empire",
            "imageLink": "http://www.sup.org/img/covers/large/pid_2829.jpg",
            "language": "Akkadian",
            "link": "https://en.wikipedia.org/wiki/Epic_of_Gilgamesh\n",
            "pages": 160,
            "title": "The Epic Of Gilgamesh",
            "year": -1700
          },
          {
            "author": "Unknown",
            "country": "Achaemenid Empire",
            "imageLink": "https://kbimages1-a.akamaihd.net/945b5eae-7768-4957-b36a-95f23dc5a86f/1200/1200/False/the-book-of-job-49.jpg",
            "language": "Hebrew",
            "link": "https://en.wikipedia.org/wiki/Book_of_Job\n",
            "pages": 176,
            "title": "The Book Of Job",
            "year": -600
          },
          {
            "author": "Unknown",
            "country": "India/Iran/Iraq/Egypt/Tajikistan",
            "imageLink": "https://m.media-amazon.com/images/I/51ZgP+R5kNL.jpg",
            "language": "Arabic",
            "link": "https://en.wikipedia.org/wiki/One_Thousand_and_One_Nights\n",
            "pages": 288,
            "title": "One Thousand and One Nights",
            "year": 1200
          },
          {
            "author": "Jane Austen",
            "country": "United Kingdom",
            "imageLink": "https://images-na.ssl-images-amazon.com/images/I/81ukiR5Z2JL.jpg",
            "language": "English",
            "link": "https://en.wikipedia.org/wiki/Pride_and_Prejudice\n",
            "pages": 226,
            "title": "Pride and Prejudice",
            "year": 1813
          },
          {
            "author": "Samuel Beckett",
            "country": "Republic of Ireland",
            "imageLink": "https://m.media-amazon.com/images/I/51VQHxfsj4L._AC_SY580_.jpg",
            "language": "French, English",
            "link": "https://en.wikipedia.org/wiki/Molloy_(novel)\n",
            "pages": 256,
            "title": "Molloy, Malone Dies, The Unnamable, the trilogy",
            "year": 1952
          },
          {
            "author": "Giovanni Boccaccio",
            "country": "Italy",
            "imageLink": "https://images-na.ssl-images-amazon.com/images/I/91rwRXdasRL.jpg",
            "language": "Italian",
            "link": "https://en.wikipedia.org/wiki/The_Decameron\n",
            "pages": 1024,
            "title": "The Decameron",
            "year": 1351
          },
          {
            "author": "Jorge Luis Borges",
            "country": "Argentina",
            "imageLink": "https://images-na.ssl-images-amazon.com/images/I/41gNyjqK1CL._SY291_BO1,204,203,200_QL40_ML2_.jpg",
            "language": "Spanish",
            "link": "https://en.wikipedia.org/wiki/Ficciones\n",
            "pages": 224,
            "title": "Ficciones",
            "year": 1965
          },
          {
            "author": "Emily Bront\u00eb",
            "country": "United Kingdom",
            "imageLink": "https://images-na.ssl-images-amazon.com/images/I/71ogwlE3YNL.jpg",
            "language": "English",
            "link": "https://en.wikipedia.org/wiki/Wuthering_Heights\n",
            "pages": 342,
            "title": "Wuthering Heights",
            "year": 1847
          },
          {
            "author": "Albert Camus",
            "country": "Algeria, French Empire",
            "imageLink": "https://d3525k1ryd2155.cloudfront.net/h/475/297/1321297475.0.x.jpg",
            "language": "French",
            "link": "https://en.wikipedia.org/wiki/The_Stranger_(novel)\n",
            "pages": 185,
            "title": "The Stranger",
            "year": 1942
          },
          {
            "author": "Louis-Ferdinand C\u00e9line",
            "country": "France",
            "imageLink": "https://ia803007.us.archive.org/BookReader/BookReaderPreview.php?id=journeytoendofth00ce&subPrefix=journeytoendofth00ce&itemPath=/2/items/journeytoendofth00ce&server=ia803007.us.archive.org&page=leaf1&fail=preview&&scale=8&rotate=0",
            "language": "French",
            "link": "https://en.wikipedia.org/wiki/Journey_to_the_End_of_the_Night\n",
            "pages": 505,
            "title": "Journey to the End of the Night",
            "year": 1932
          },
          {
            "author": "Miguel de Cervantes",
            "country": "Spain",
            "imageLink": "https://www.curriculumnacional.cl/614/articles-88483_thumbnail.thumb_iNormal.jpg",
            "language": "Spanish",
            "link": "https://en.wikipedia.org/wiki/Don_Quixote\n",
            "pages": 1056,
            "title": "Don Quijote De La Mancha",
            "year": 1610
          },
          {
            "author": "Geoffrey Chaucer",
            "country": "England",
            "imageLink": "https://flxt.tmsimg.com/assets/p18477_p_v8_aa.jpg",
            "language": "English",
            "link": "https://en.wikipedia.org/wiki/The_Canterbury_Tales\n",
            "pages": 544,
            "title": "The Canterbury Tales",
            "year": 1450
          },
          {
            "author": "Joseph Conrad",
            "country": "United Kingdom",
            "imageLink": "https://kbimages1-a.akamaihd.net/142742a6-fab7-406e-b2ef-72e3786768df/1200/1200/False/nostromo-a-tale-of-the-seaboard-32.jpg",
            "language": "English",
            "link": "https://en.wikipedia.org/wiki/Nostromo\n",
            "pages": 320,
            "title": "Nostromo",
            "year": 1904
          },
          {
            "author": "Charles Dickens",
            "country": "United Kingdom",
            "imageLink": "https://images-na.ssl-images-amazon.com/images/I/81iVwwy4J8L.jpg",
            "language": "English",
            "link": "https://en.wikipedia.org/wiki/Great_Expectations\n",
            "pages": 194,
            "title": "Great Expectations",
            "year": 1861
          },
          {
            "author": "Alfred D\u00f6blin",
            "country": "Germany",
            "imageLink": "https://as.nyu.edu/content/dam/nyu-as/deutschesHaus/images/culture/2018/Spring-2018/DH_culture_05042018_BerlinAlexanderplatz_Crop1.jpg",
            "language": "German",
            "link": "https://en.wikipedia.org/wiki/Berlin_Alexanderplatz\n",
            "pages": 600,
            "title": "Berlin Alexanderplatz",
            "year": 1929
          },
          {
            "author": "Fyodor Dostoevsky",
            "country": "Russia",
            "imageLink": "images/crime-and-punishment.jpg",
            "language": "Russian",
            "link": "https://en.wikipedia.org/wiki/Crime_and_Punishment\n",
            "pages": 551,
            "title": "Crime and Punishment",
            "year": 1866
          },
          {
            "author": "Fyodor Dostoevsky",
            "country": "Russia",
            "imageLink": "https://www.yektaketab.ir/public/app/fa/files/images/book/original/d4caa3364711c8bcaa6a182085f4b4cd.jpg",
            "language": "Russian",
            "link": "https://en.wikipedia.org/wiki/The_Idiot\n",
            "pages": 656,
            "title": "The Idiot",
            "year": 1869
          },
          {
            "author": "Fyodor Dostoevsky",
            "country": "Russia",
            "imageLink": "https://www.fullmoondirect.com/assets/images/POSSDVD_possessed.jpg",
            "language": "Russian",
            "link": "https://en.wikipedia.org/wiki/Demons_(Dostoyevsky_novel)\n",
            "pages": 768,
            "title": "The Possessed",
            "year": 1872
          },
          {
            "author": "Fyodor Dostoevsky",
            "country": "Russia",
            "imageLink": "https://kbimages1-a.akamaihd.net/1208ebc8-3b5d-40ef-ba2d-b5121520d7e2/1200/1200/False/the-brothers-karamazov-135.jpg",
            "language": "Russian",
            "link": "https://en.wikipedia.org/wiki/The_Brothers_Karamazov\n",
            "pages": 824,
            "title": "The Brothers Karamazov",
            "year": 1880
          },
          {
            "author": "George Eliot",
            "country": "United Kingdom",
            "imageLink": "https://images.squarespace-cdn.com/content/v1/50a458f7e4b000dda4d925d8/1589381609596-XIM4894PSI5RKXXT9J4F/middlemarch.jpg",
            "language": "English",
            "link": "https://en.wikipedia.org/wiki/Middlemarch\n",
            "pages": 800,
            "title": "Middlemarch",
            "year": 1871
          },
          {
            "author": "Ralph Ellison",
            "country": "United States",
            "imageLink": "https://images-na.ssl-images-amazon.com/images/I/71KA2gr8xBL.jpg",
            "language": "English",
            "link": "https://en.wikipedia.org/wiki/Invisible_Man\n",
            "pages": 581,
            "title": "Invisible Man",
            "year": 1952
          },
          {
            "author": "Euripides",
            "country": "Greece",
            "imageLink": "https://kbimages1-a.akamaihd.net/b9d47c77-2050-4bfe-9412-983ea1455d90/353/569/90/False/medea-108.jpg",
            "language": "Greek",
            "link": "https://en.wikipedia.org/wiki/Medea_(play)\n",
            "pages": 104,
            "title": "Medea",
            "year": -431
          },
          {
            "author": "William Faulkner",
            "country": "United States",
            "imageLink": "https://pictures.abebooks.com/isbn/9780394602714-us.jpg",
            "language": "English",
            "link": "https://en.wikipedia.org/wiki/Absalom,_Absalom!\n",
            "pages": 313,
            "title": "Absalom, Absalom!",
            "year": 1936
          },
          {
            "author": "William Faulkner",
            "country": "United States",
            "imageLink": "https://encrypted-tbn0.gstatic.com/images?q=tbn:ANd9GcRVmelvlivbAMqzKBVIPQZ_gyQlDb8sOEOtFqw76RFlMfjl-TKpxCjPuHHw5CAnqJk0g-w&usqp=CAU",
            "language": "English",
            "link": "https://en.wikipedia.org/wiki/The_Sound_and_the_Fury\n",
            "pages": 326,
            "title": "The Sound and the Fury",
            "year": 1929
          },
          {
            "author": "Gustave Flaubert",
            "country": "France",
            "imageLink": "https://m.media-amazon.com/images/I/419NxOEYLkL.jpg",
            "language": "French",
            "link": "https://en.wikipedia.org/wiki/Madame_Bovary\n",
            "pages": 528,
            "title": "Madame Bovary",
            "year": 1857
          },
          {
            "author": "Gustave Flaubert",
            "country": "France",
            "imageLink": "https://m.media-amazon.com/images/I/61kG3DOc4pL.jpg",
            "language": "French",
            "link": "https://en.wikipedia.org/wiki/Sentimental_Education\n",
            "pages": 606,
            "title": "Sentimental Education",
            "year": 1869
          },
          {
            "author": "Federico Garc\u00eda Lorca",
            "country": "Spain",
            "imageLink": "https://images-na.ssl-images-amazon.com/images/I/41crc1V-zKL._SX348_BO1,204,203,200_.jpg",
            "language": "Spanish",
            "link": "https://en.wikipedia.org/wiki/Gypsy_Ballads\n",
            "pages": 218,
            "title": "Gypsy Ballads",
            "year": 1928
          },
          {
            "author": "Gabriel Garc\u00eda M\u00e1rquez",
            "country": "Colombia",
            "imageLink": "https://dwcp78yw3i6ob.cloudfront.net/wp-content/uploads/2016/12/12162813/100_Years_First_Ed_Hi_Res-768x1153.jpg",
            "language": "Spanish",
            "link": "https://en.wikipedia.org/wiki/One_Hundred_Years_of_Solitude\n",
            "pages": 417,
            "title": "One Hundred Years of Solitude",
            "year": 1967
          },
          {
            "author": "Gabriel Garc\u00eda M\u00e1rquez",
            "country": "Colombia",
            "imageLink": "https://manhattanbookreview.com/wp-content/uploads/love_in_the_time_of_cholera.jpg",
            "language": "Spanish",
            "link": "https://en.wikipedia.org/wiki/Love_in_the_Time_of_Cholera\n",
            "pages": 368,
            "title": "Love in the Time of Cholera",
            "year": 1985
          }
    ]

}